<?xml version="1.0" encoding="UTF-8"?>
<r>
   <e freq="$21546">
      <lg>
         <l pos="n">team</l>
      </lg>
      <mg>
         <tg xml:lang="sme">
            <t pos="n">bargojoavku</t>
         </tg>
      </mg>
   </e>
   <e freq="$21530">
      <lg>
         <l pos="n">strid</l>
      </lg>
      <mg>
         <tg xml:lang="sme">
            <t pos="n">nárrodat</t>
            <t pos="n">nággu</t>
         </tg>
      </mg>
   </e>
   <e freq="$21483">
      <lg>
         <l pos="n">kapasitet</l>
      </lg>
      <mg>
         <tg xml:lang="sme">
            <t pos="n">kapasiteahtta</t>
         </tg>
      </mg>
   </e>
   <e freq="$21404">
      <lg>
         <l pos="n">opptak</l>
      </lg>
      <mg>
         <tg xml:lang="sme">
            <t pos="n">sisaváldin</t>
         </tg>
      </mg>
   </e>
   <e mg_c="2" freq="$21363">
      <lg>
         <l pos="n">trend</l>
      </lg>
      <mg>
         <tg xml:lang="sme">
            <t pos="n">treanda</t>
         </tg>
      </mg>
      <mg>
         <tg xml:lang="sme">
            <t pos="n">trenda</t>
         </tg>
      </mg>
   </e>
   <e freq="$21323">
      <lg>
         <l pos="n">drap</l>
      </lg>
      <mg>
         <tg xml:lang="sme">
            <t pos="n">goddin</t>
         </tg>
      </mg>
   </e>
   <e freq="21299">
      <lg>
         <l pos="n">budskap</l>
      </lg>
      <mg>
         <tg xml:lang="sme">
            <t pos="n">sáttasátni</t>
         </tg>
      </mg>
   </e>
   <e mg_c="2" freq="$21265">
      <lg>
         <l pos="n">format</l>
      </lg>
      <mg>
         <tg xml:lang="sme">
            <t pos="n">formáhtta</t>
         </tg>
      </mg>
      <mg>
         <tg xml:lang="sme">
            <t pos="n">sturrodat</t>
         </tg>
      </mg>
   </e>
   <e freq="21264">
      <lg>
         <l pos="n">regissør</l>
      </lg>
      <mg>
         <tg xml:lang="sme">
            <t pos="n">rešisevrra</t>
         </tg>
      </mg>
   </e>
   <e freq="$21226">
      <lg>
         <l pos="n">vert</l>
      </lg>
      <mg>
         <tg xml:lang="sme">
            <t pos="n">doalloisit</t>
         </tg>
      </mg>
   </e>
   <e freq="$21100">
      <lg>
         <l pos="n">overgrep</l>
      </lg>
      <mg>
         <tg xml:lang="sme">
            <t pos="n">veahkaválddálašvuohta</t>
         </tg>
      </mg>
   </e>
   <e freq="$21070">
      <lg>
         <l pos="n">nedgang</l>
      </lg>
      <mg>
         <tg xml:lang="sme">
            <t pos="n">njiedjan</t>
         </tg>
      </mg>
   </e>
   <e freq="$21068">
      <lg>
         <l pos="n">hær</l>
      </lg>
      <mg>
         <tg xml:lang="sme">
            <t pos="n">veahka</t>
         </tg>
      </mg>
   </e>
   <e freq="20917">
      <lg>
         <l pos="n">administrasjon</l>
      </lg>
      <mg>
         <tg xml:lang="sme">
            <t pos="n">administrašuvdna</t>
         </tg>
      </mg>
   </e>
   <e freq="20897">
      <lg>
         <l pos="n">stadion</l>
      </lg>
      <mg>
         <tg xml:lang="sme">
            <t pos="n">stadion</t>
         </tg>
      </mg>
   </e>
   <e freq="20734">
      <lg>
         <l pos="n">rektor</l>
      </lg>
      <mg>
         <tg xml:lang="sme">
            <t pos="NomAg">skuvlajođiheaddji</t>
         </tg>
      </mg>
   </e>
   <e freq="$20733">
      <lg>
         <l pos="n">trinn</l>
      </lg>
      <mg>
         <tg xml:lang="sme">
            <t pos="n">ceahkki</t>
         </tg>
      </mg>
   </e>
   <e freq="$20611">
      <lg>
         <l pos="n">frukt</l>
      </lg>
      <mg>
         <tg xml:lang="sme">
            <t pos="n">šaddu</t>
            <t pos="n">šattus</t>
         </tg>
      </mg>
   </e>
   <e freq="20531">
      <lg>
         <l pos="n">stein</l>
      </lg>
      <mg>
         <tg xml:lang="sme">
            <t pos="n">ráktu</t>
         </tg>
      </mg>
   </e>
   <e mg_c="2" freq="20514">
      <lg>
         <l pos="n">begrunnelse</l>
      </lg>
      <mg>
         <tg xml:lang="sme">
            <t pos="n">vuođustus</t>
            <t pos="n">ággadeapmi</t>
            <t pos="n">vuođuštus</t>
         </tg>
      </mg>
   </e>
   <e freq="20474">
      <lg>
         <l pos="n">grep</l>
      </lg>
      <mg>
         <tg xml:lang="sme">
            <t pos="n">táhka</t>
            <xg>
               <x/>
               <xt/>
            </xg>
         </tg>
      </mg>
   </e>
   <e freq="20446">
      <lg>
         <l pos="n">Moss</l>
      </lg>
      <mg>
         <tg xml:lang="sme">
            <t pos="n">Moss</t>
         </tg>
      </mg>
   </e>
   <e mg_c="2" freq="20423">
      <lg>
         <l pos="n">hjerne</l>
      </lg>
      <mg>
         <tg xml:lang="sme">
            <t pos="n">vuoiŋŋaš</t>
         </tg>
      </mg>
      <mg>
         <tg xml:lang="sme">
            <t pos="n">vuoiŋŋamaččat</t>
         </tg>
      </mg>
   </e>
   <e freq="20419">
      <lg>
         <l pos="n">føler</l>
      </lg>
      <mg>
         <tg xml:lang="sme">
            <t pos="n">dovddan</t>
         </tg>
      </mg>
   </e>
   <e mg_c="2" freq="20293">
      <lg>
         <l pos="n">kriterium</l>
      </lg>
      <mg>
         <tg xml:lang="sme">
            <t pos="n">kriteria</t>
         </tg>
      </mg>
      <mg>
         <tg xml:lang="sme">
            <t pos="n">kriteriija</t>
         </tg>
      </mg>
   </e>
   <e freq="$20245">
      <lg>
         <l pos="n">amerikaner</l>
      </lg>
      <mg>
         <tg xml:lang="sme">
            <t pos="n">amerihkálaš</t>
         </tg>
      </mg>
   </e>
   <e freq="$20145">
      <lg>
         <l pos="n">nasjon</l>
      </lg>
      <mg>
         <tg xml:lang="sme">
            <t pos="n">našuvdna</t>
         </tg>
      </mg>
   </e>
   <e freq="$19722">
      <lg>
         <l pos="n">forbruk</l>
      </lg>
      <mg>
         <tg xml:lang="sme">
            <t pos="n">mannu</t>
         </tg>
      </mg>
   </e>
   <e mg_c="2" freq="$19615">
      <lg>
         <l pos="n">realitet</l>
      </lg>
      <mg>
         <tg xml:lang="sme">
            <t pos="n">realitehta</t>
            <t pos="n">realiteahtta</t>
         </tg>
      </mg>
   </e>
   <e mg_c="2" freq="$19565">
      <lg>
         <l pos="n">kilometer</l>
      </lg>
      <mg>
         <tg xml:lang="sme">
            <t pos="n">gilomehter</t>
            <t pos="n">kilomehter</t>
         </tg>
      </mg>
   </e>
   <e freq="$19545">
      <lg>
         <l pos="n">variant</l>
      </lg>
      <mg>
         <tg xml:lang="sme">
            <t pos="n">variánta</t>
         </tg>
      </mg>
   </e>
   <e freq="$19470">
      <lg>
         <l pos="n">rente</l>
      </lg>
      <mg>
         <tg xml:lang="sme">
            <t pos="n">reantu</t>
         </tg>
      </mg>
   </e>
   <e freq="$19419">
      <lg>
         <l pos="n">mangfold</l>
      </lg>
      <mg>
         <tg xml:lang="sme">
            <t pos="n">valljivuohta</t>
         </tg>
      </mg>
   </e>
   <e freq="$19320">
      <lg>
         <l pos="n">medarbeider</l>
      </lg>
      <mg>
         <tg xml:lang="sme">
            <t pos="n">mielbargi</t>
         </tg>
      </mg>
   </e>
   <e mg_c="2" freq="$19223">
      <lg>
         <l pos="n">opphold</l>
      </lg>
      <mg>
         <tg xml:lang="sme">
            <t pos="n">gaska</t>
            <t pos="n">ádji</t>
         </tg>
      </mg>
            <t pos="n">orrun</t>
      <mg>
         <tg xml:lang="sme">
         </tg>
      </mg>
   </e>
   <e freq="$19207">
      <lg>
         <l pos="n">statsbudsjett</l>
      </lg>
      <mg>
         <tg xml:lang="sme">
            <t pos="n">stádabušeahtta</t>
         </tg>
      </mg>
   </e>
   <e freq="$19190">
      <lg>
         <l pos="n">kopi</l>
      </lg>
      <mg>
         <tg xml:lang="sme">
            <t pos="n">kopiija</t>
         </tg>
      </mg>
   </e>
   <e mg_c="2" freq="$19084">
      <lg>
         <l pos="n">oppløsning</l>
      </lg>
      <mg>
         <tg xml:lang="sme">
            <t pos="n">luvvi</t>
         </tg>
      </mg>
      <mg>
         <tg xml:lang="sme">
            <t pos="n">čuokkisčoahkku</t>
         </tg>
      </mg>
   </e>
   <e freq="$19054">
      <lg>
         <l pos="n">revisor</l>
      </lg>
      <mg>
         <tg xml:lang="sme">
            <t pos="NomAg">rehketdoallodárkkisteaddji</t>
         </tg>
      </mg>
   </e>
   <e freq="$19020">
      <lg>
         <l pos="n">kampanje</l>
      </lg>
      <mg>
         <tg xml:lang="sme">
            <t pos="n">áŋggirdeapmi</t>
            <t pos="n">ávžžuhusdoaibma</t>
            <t pos="n">kampánja</t>
            <t pos="n">kampánnja</t>
         </tg>
      </mg>
   </e>
   <e freq="$18936">
      <lg>
         <l pos="n">operasjon</l>
      </lg>
      <mg>
         <tg xml:lang="sme">
            <t pos="n">operašuvdna</t>
         </tg>
      </mg>
   </e>
   <e freq="$18918">
      <lg>
         <l pos="n">måltid</l>
      </lg>
      <mg>
         <tg xml:lang="sme">
            <t pos="n">borran</t>
         </tg>
      </mg>
   </e>
   <e freq="$18840">
      <lg>
         <l pos="n">struktur</l>
      </lg>
      <mg>
         <tg xml:lang="sme">
            <t pos="n">struktuvra</t>
         </tg>
      </mg>
   </e>
   <e freq="18812">
      <lg>
         <l pos="n">gjenstand</l>
      </lg>
      <mg>
         <tg xml:lang="sme">
            <t pos="n">áhtu</t>
         </tg>
      </mg>
   </e>
   <e freq="$18732">
      <lg>
         <l pos="n">fiende</l>
      </lg>
      <mg>
         <tg xml:lang="sme">
            <t pos="n">vašálaš</t>
         </tg>
      </mg>
   </e>
   <e freq="$18665">
      <lg>
         <l pos="n">valgkamp</l>
      </lg>
      <mg>
         <tg xml:lang="sme">
            <t pos="n">válgagižžu</t>
         </tg>
      </mg>
   </e>
   <e freq="$18506">
      <lg>
         <l pos="n">humor</l>
      </lg>
      <mg>
         <tg xml:lang="sme">
            <t pos="n">humor</t>
         </tg>
      </mg>
   </e>
   <e freq="$18496">
      <lg>
         <l pos="n">beløp</l>
      </lg>
      <mg>
         <tg xml:lang="sme">
            <t pos="n">submi</t>
         </tg>
      </mg>
   </e>
   <e freq="$18404">
      <lg>
         <l pos="n">oppfølging</l>
      </lg>
      <mg>
         <tg xml:lang="sme">
            <t pos="n">čuovvoleapmi</t>
         </tg>
      </mg>
   </e>
   <e freq="$18343">
      <lg>
         <l pos="n">funn</l>
      </lg>
      <mg>
         <tg xml:lang="sme">
            <t pos="n">gávnnus</t>
         </tg>
      </mg>
   </e>
   <e freq="18276">
      <lg>
         <l pos="n">bad</l>
      </lg>
      <mg>
         <tg xml:lang="sme">
            <t pos="n">hávdda</t>
         </tg>
      </mg>
   </e>
   <e freq="$18176">
      <lg>
         <l pos="n">landbruk</l>
      </lg>
      <mg>
         <tg xml:lang="sme">
            <t pos="n">eanadoallu</t>
         </tg>
      </mg>
   </e>
   <e freq="$18104">
      <lg>
         <l pos="n">balanse</l>
      </lg>
      <mg>
         <tg xml:lang="sme">
            <t pos="n">dássádat</t>
         </tg>
      </mg>
   </e>
   <e freq="$18048">
      <lg>
         <l pos="n">deltakelse</l>
      </lg>
      <mg>
         <tg xml:lang="sme">
            <t pos="n">oassálastin</t>
         </tg>
      </mg>
   </e>
   <e freq="$18022">
      <lg>
         <l pos="n">programvare</l>
      </lg>
      <mg>
         <tg xml:lang="sme">
            <t pos="n">prográmmagálvu</t>
         </tg>
      </mg>
   </e>
   <e freq="$17943">
      <lg>
         <l pos="n">støy</l>
      </lg>
      <mg>
         <tg xml:lang="sme">
            <t pos="n">gadja</t>
         </tg>
      </mg>
   </e>
   <e freq="$17902">
      <lg>
         <l pos="n">forbund</l>
      </lg>
      <mg>
         <tg xml:lang="sme">
            <t pos="n">searvi</t>
            <t pos="n">lihttu</t>
         </tg>
      </mg>
   </e>
   <e freq="$17878">
      <lg>
         <l pos="n">revolusjon</l>
      </lg>
      <mg>
         <tg xml:lang="sme">
            <t pos="n">revolušuvdna</t>
         </tg>
      </mg>
   </e>
   <e freq="$17820">
      <lg>
         <l pos="n">kapital</l>
      </lg>
      <mg>
         <tg xml:lang="sme">
            <t pos="n">kapitála</t>
         </tg>
      </mg>
   </e>
   <e freq="$17767">
      <lg>
         <l pos="n">forbud</l>
      </lg>
      <mg>
         <tg xml:lang="sme">
            <t pos="n">gieldda</t>
         </tg>
      </mg>
   </e>
   <e freq="$17694">
      <lg>
         <l pos="n">innflytelse</l>
      </lg>
      <mg>
         <tg xml:lang="sme">
            <t pos="n">váikkuheapmi</t>
            <t pos="n">váikkuhanfápmu</t>
         </tg>
      </mg>
   </e>
   <e freq="17579">
      <lg>
         <l pos="n">konsept</l>
      </lg>
      <mg>
         <tg xml:lang="sme">
            <t pos="n">álgočálus</t>
         </tg>
      </mg>
   </e>
   <e mg_c="3" freq="$17382">
      <lg>
         <l pos="n">areal</l>
      </lg>
      <mg>
         <tg xml:lang="sme">
            <t pos="n">guovlu</t>
            <t pos="n">areála</t>
         </tg>
      </mg>
      <mg>
         <tg xml:lang="sme">
            <t pos="n">areála</t>
         </tg>
      </mg>
      <mg>
         <tg xml:lang="sme">
            <t pos="n">viidodat</t>
         </tg>
      </mg>
   </e>
   <e freq="$17321">
      <lg>
         <l pos="n">tone</l>
      </lg>
      <mg>
         <tg xml:lang="sme">
            <t pos="n">nuohtta</t>
            <t pos="n">šuokŋa</t>
         </tg>
      </mg>
   </e>
   <e freq="$17202">
      <lg>
         <l pos="n">bivirkning</l>
      </lg>
      <mg>
         <tg xml:lang="sme">
            <t pos="n">liigeváikkuhus</t>
         </tg>
      </mg>
   </e>
   <e freq="$17175">
      <lg>
         <l pos="n">frispark</l>
      </lg>
      <mg>
         <tg xml:lang="sme">
            <t pos="n">njuolggačievččasteapmi</t>
         </tg>
      </mg>
   </e>
   <e mg_c="2" freq="$17101">
      <lg>
         <l pos="n">sans</l>
      </lg>
      <mg>
         <tg xml:lang="sme">
            <t pos="n">dáidu</t>
         </tg>
      </mg>
      <mg>
         <tg xml:lang="sme">
            <t pos="n">dovdda</t>
         </tg>
      </mg>
   </e>
   <e freq="17053">
      <lg>
         <l pos="n">arkiv</l>
      </lg>
      <mg>
         <tg xml:lang="sme">
            <t pos="n">arkiiva</t>
         </tg>
      </mg>
   </e>
   <e freq="$17031">
      <lg>
         <l pos="n">hals</l>
      </lg>
      <mg>
         <tg xml:lang="sme">
            <t pos="n">čeabetgođa</t>
         </tg>
      </mg>
   </e>
   <e freq="$16918">
      <lg>
         <l pos="n">relasjon</l>
      </lg>
      <mg>
         <tg xml:lang="sme">
            <t pos="n">relašuvdna</t>
         </tg>
      </mg>
   </e>
   <e freq="$16906">
      <lg>
         <l pos="n">sal</l>
      </lg>
      <mg>
         <tg xml:lang="sme">
            <t pos="n">sálla</t>
         </tg>
      </mg>
   </e>
   <e freq="$16903">
      <lg>
         <l pos="n">tilknytning</l>
      </lg>
      <mg>
         <tg xml:lang="sme">
            <t pos="n">čatnaseapmi</t>
            <t pos="n">oktavuohta</t>
         </tg>
      </mg>
   </e>
   <e freq="$16849">
      <lg>
         <l pos="n">innslag</l>
      </lg>
      <mg>
         <tg xml:lang="sme">
            <t pos="n">ovdanbuktin</t>
         </tg>
      </mg>
   </e>
   <e freq="$16848">
      <lg>
         <l pos="n">ring</l>
      </lg>
      <mg>
         <tg xml:lang="sme">
            <t pos="n">riekkis</t>
         </tg>
      </mg>
   </e>
</r>
